ament_lint_cmake/__init__.py
ament_lint_cmake/cmakelint.py
ament_lint_cmake/main.py
ament_lint_cmake_py-0.14.2.data/data/share/ament_index/resource_index/packages/ament_lint_cmake
ament_lint_cmake_py-0.14.2.data/data/share/ament_lint_cmake/package.xml
ament_lint_cmake_py-0.14.2.dist-info/METADATA
ament_lint_cmake_py-0.14.2.dist-info/WHEEL
ament_lint_cmake_py-0.14.2.dist-info/entry_points.txt
ament_lint_cmake_py-0.14.2.dist-info/top_level.txt
ament_lint_cmake_py-0.14.2.dist-info/zip-safe
ament_lint_cmake_py-0.14.2.dist-info/RECORD
